{
  "name": {
    "last": "Reyna",
    "first": "Lee"
  },
  "course": "BSSTAT",
  "studentNo": "2020-20202",
  "records": [
    {
      "sem": "1",
      "year": "2019-2020",
      "subjects": [
        [
          "ETHICS 1",
          "1.25",
          "3",
          "3.75",
          "3.75"
        ],
        [
          "KAS 1",
          "1.5",
          "3",
          "4.5",
          "8.25"
        ],
        [
          "MATH 27",
          "1.25",
          "3",
          "3.75",
          "12"
        ],
        [
          "BIO 30",
          "1.25",
          "3",
          "3.75",
          "15.75"
        ],
        [
          "STAT 101",
          "1",
          "3",
          "3",
          "18.75"
        ],
        [
          "STAT 135",
          "1.5",
          "3",
          "4.5",
          "23.25"
        ],
        [
          "HK 11",
          "1.75",
          "0",
          "0",
          "23.25"
        ]
      ],
      "units": "18",
      "status": "ENROLLED"
    },
    {
      "sem": "2",
      "year": "2019-2020",
      "subjects": [
        [
          "ARTS 1",
          "1.25",
          "3",
          "0",
          "23.25"
        ],
        [
          "MATH 10",
          "1",
          "3",
          "0",
          "23.25"
        ],
        [
          "MATH 28",
          "1.75",
          "3",
          "0",
          "23.25"
        ],
        [
          "CMSC 12",
          "2",
          "3",
          "0",
          "23.25"
        ],
        [
          "STAT 162",
          "1.25",
          "3",
          "0",
          "23.25"
        ],
        [
          "STAT 182",
          "1.25",
          "3",
          "0",
          "23.25"
        ],
        [
          "HK 12",
          "2",
          "0",
          "0",
          "23.25"
        ]
      ],
      "units": "18",
      "status": "ENROLLED"
    },
    {
      "sem": "1",
      "year": "2020-2021",
      "subjects": [
        [
          "STS 1",
          "1.5",
          "3",
          "4.5",
          "27.75"
        ],
        [
          "KAS 4",
          "1.75",
          "3",
          "5.25",
          "33"
        ],
        [
          "CMSC 21",
          "1.75",
          "3",
          "5.25",
          "38.25"
        ],
        [
          "ECON 11",
          "1.25",
          "3",
          "3.75",
          "42"
        ],
        [
          "STAT 144",
          "1.5",
          "3",
          "4.5",
          "46.5"
        ],
        [
          "STAT 168",
          "1.5",
          "3",
          "4.5",
          "51"
        ],
        [
          "HK 12",
          "1",
          "0",
          "0",
          "51"
        ],
        [
          "NSTP 1",
          "1",
          "0",
          "0",
          "51"
        ]
      ],
      "units": "18",
      "status": "ENROLLED"
    },
    {
      "sem": "2",
      "year": "2020-2021",
      "subjects": [
        [
          "PHILO 1",
          "1",
          "3",
          "3",
          "54"
        ],
        [
          "MATH 182",
          "1.25",
          "3",
          "3.75",
          "57.75"
        ],
        [
          "CMSC 22",
          "1",
          "3",
          "3",
          "60.75"
        ],
        [
          "ABME 10",
          "1.5",
          "3",
          "4.5",
          "65.25"
        ],
        [
          "STAT 145",
          "1.5",
          "3",
          "4.5",
          "69.75"
        ],
        [
          "STAT 163",
          "1.75",
          "3",
          "5.25",
          "75"
        ],
        [
          "HK 12",
          "2",
          "0",
          "0",
          "75"
        ],
        [
          "NSTP 2",
          "2",
          "0",
          "0",
          "75"
        ]
      ],
      "units": "18",
      "status": "ENROLLED"
    },
    {
      "sem": "1",
      "year": "2021-2022",
      "subjects": [
        [
          "COMM 10",
          "3",
          "3",
          "9",
          "84"
        ],
        [
          "ELECTIVETRACK 1",
          "3",
          "3",
          "9",
          "93"
        ],
        [
          "STAT 146",
          "3",
          "3",
          "9",
          "102"
        ],
        [
          "STAT 173",
          "3",
          "3",
          "9",
          "111"
        ],
        [
          "STAT 175",
          "3",
          "3",
          "9",
          "120"
        ],
        [
          "STAT 181",
          "3",
          "3",
          "9",
          "129"
        ]
      ],
      "units": "18",
      "status": "ENROLLED"
    },
    {
      "sem": "2",
      "year": "2021-2022",
      "subjects": [
        [
          "ELECTIVETRACK 2",
          "1",
          "3",
          "3",
          "132"
        ],
        [
          "CMSC 127",
          "1",
          "3",
          "3",
          "135"
        ],
        [
          "STAT 147",
          "1.25",
          "3",
          "3.75",
          "138.75"
        ],
        [
          "STAT 151",
          "1.5",
          "3",
          "4.5",
          "143.25"
        ],
        [
          "STAT 156",
          "1.75",
          "3",
          "5.25",
          "148.5"
        ],
        [
          "STAT 174",
          "2",
          "3",
          "6",
          "154.5"
        ],
        [
          "STAT 192.1",
          "1.25",
          "1",
          "1.25",
          "155.75"
        ]
      ],
      "units": "19",
      "status": "ENROLLED"
    },
    {
      "sem": "M",
      "year": "2021-2022",
      "subjects": [
        [
          "STAT 198",
          "1",
          "3",
          "3",
          "158.75"
        ]
      ],
      "units": "3",
      "status": "ENROLLED"
    },
    {
      "sem": "1",
      "year": "2022-2023",
      "subjects": [
        [
          "ELECTIVETRACK 3",
          "1.5",
          "3",
          "4.5",
          "163.25"
        ],
        [
          "ENG 10",
          "3",
          "3",
          "9",
          "172.25"
        ],
        [
          "STAT 148",
          "1.25",
          "3",
          "3.75",
          "176"
        ],
        [
          "STAT 165",
          "1.25",
          "3",
          "3.75",
          "179.75"
        ],
        [
          "STAT 190",
          "S",
          "1",
          "0",
          "179.75"
        ],
        [
          "STAT 191",
          "2",
          "3",
          "6",
          "185.75"
        ]
      ],
      "units": "16",
      "status": "ENROLLED"
    },
    {
      "sem": "2",
      "year": "2022-2023",
      "subjects": [
        [
          "PI 10",
          "1",
          "3",
          "3",
          "188.75"
        ],
        [
          "STAT 157",
          "1",
          "3",
          "3",
          "191.75"
        ],
        [
          "STAT 167",
          "1",
          "3",
          "3",
          "194.75"
        ],
        [
          "STAT 183",
          "1",
          "3",
          "3",
          "197.75"
        ],
        [
          "STAT 190",
          "1",
          "2",
          "3",
          "200.75"
        ],
        [
          "STAT 199",
          "1",
          "1",
          "1",
          "201.75"
        ]
      ],
      "units": "15",
      "status": "ENROLLED"
    }
  ],
  "totalUnitsTaken": "143",
  "totalUnitsRequired": "143",
  "GWA": "1.41083",
  "verifiedBy": []
}